MANIFEST.in
__info__.py
setup.py
./appomatic_tagging.egg-info/SOURCES.txt
./appomatic_tagging.egg-info/dependency_links.txt
./appomatic_tagging.egg-info/requires.txt
./appomatic_tagging.egg-info/top_level.txt
appomatic_tagging/__app__.py
appomatic_tagging/__init__.py
appomatic_tagging.egg-info/PKG-INFO
appomatic_tagging.egg-info/SOURCES.txt
appomatic_tagging.egg-info/dependency_links.txt
appomatic_tagging.egg-info/requires.txt
appomatic_tagging.egg-info/top_level.txt