Metadata-Version: 1.0
Name: appomatic-tagging
Version: 0.0.31
Summary: A generic tagging application for Django projects
Home-page: http://code.google.com/p/django-tagging/
Author: RedHog (Egil Moeller)
Author-email: egil.moller@freecode.no
License: GPL
Keywords: appomatic django-tagging
Platform: UNKNOWN
